platform_utils/__init__.py
platform_utils/blackhole.py
platform_utils/clipboard.py
platform_utils/idle.py
platform_utils/paths.py
platform_utils/process.py
platform_utils/shell_integration/__init__.py
platform_utils/shell_integration/windows.py
tests/__init__.py
tests/test_paths.py
bp_platform_utils-0.41.dist-info/LICENSE
bp_platform_utils-0.41.dist-info/METADATA
bp_platform_utils-0.41.dist-info/WHEEL
bp_platform_utils-0.41.dist-info/top_level.txt
bp_platform_utils-0.41.dist-info/RECORD
